{
  "generatedAt": "2025-12-23T06:58:31.319Z",
  "repository": {
    "path": "/Users/elizabethstein/Projects/codebase-onboarding-tool",
    "analyzedAt": "2025-12-23T06:56:58.229Z",
    "totalFiles": 122
  },
  "statistics": {
    "fileTypes": [
      {
        "ext": ".json",
        "count": 23
      },
      {
        "ext": "",
        "count": 5
      },
      {
        "ext": ".example",
        "count": 1
      },
      {
        "ext": ".md",
        "count": 4
      },
      {
        "ext": ".txt",
        "count": 2
      },
      {
        "ext": ".tsbuildinfo",
        "count": 1
      },
      {
        "ext": ".sh",
        "count": 1
      },
      {
        "ext": ".gz",
        "count": 1
      },
      {
        "ext": ".log",
        "count": 1
      },
      {
        "ext": ".ts",
        "count": 27
      },
      {
        "ext": ".map",
        "count": 23
      },
      {
        "ext": ".js",
        "count": 19
      },
      {
        "ext": ".svg",
        "count": 1
      },
      {
        "ext": ".tsx",
        "count": 6
      },
      {
        "ext": ".css",
        "count": 1
      },
      {
        "ext": ".sql",
        "count": 3
      },
      {
        "ext": ".toml",
        "count": 1
      },
      {
        "ext": ".db",
        "count": 1
      },
      {
        "ext": ".prisma",
        "count": 1
      }
    ],
    "primaryLanguages": [
      {
        "ext": ".json",
        "count": 23
      },
      {
        "ext": "",
        "count": 5
      },
      {
        "ext": ".example",
        "count": 1
      }
    ]
  },
  "architecture": {
    "patterns": [
      "Monorepo",
      "Next.js App Router",
      "Prisma ORM"
    ],
    "entryPoints": [
      "packages/web/app/page.tsx",
      "packages/cli/src/index.ts"
    ]
  },
  "learningPath": {
    "suggestedOrder": [
      {
        "file": "README.md",
        "estimatedTime": "10 minutes",
        "priority": "high"
      },
      {
        "file": "packages/web/app/layout.tsx",
        "estimatedTime": "15 minutes",
        "priority": "high"
      },
      {
        "file": "packages/web/app/page.tsx",
        "estimatedTime": "20 minutes",
        "priority": "high"
      },
      {
        "file": "packages/web/prisma/schema.prisma",
        "estimatedTime": "25 minutes",
        "priority": "medium"
      }
    ],
    "estimatedTotal": "2-3 days to first PR"
  }
}